askyou/__init__.py
askyou/cli.py
askyou/config.json
askyou/config_manager.py
askyou/main.py
askyou/search_engine.py
askyou/summarizer.py
askyou/translator.py
askyou/utils.py
askyou-0.1.0.dist-info/LICENSE
askyou-0.1.0.dist-info/METADATA
askyou-0.1.0.dist-info/WHEEL
askyou-0.1.0.dist-info/entry_points.txt
askyou-0.1.0.dist-info/top_level.txt
askyou-0.1.0.dist-info/RECORD
