Metadata-Version: 2.1
Name: askyou
Version: 0.1.0
Summary: A ai search cli
Home-page: https://github.com/xieweicong/askyou
Author: xie weicong
Author-email: xieweicong95@gmail.com
Classifier: Programming Language :: Python :: 3
Classifier: License :: OSI Approved :: MIT License
Classifier: Operating System :: OS Independent
Requires-Python: >=3.6
License-File: LICENSE
Requires-Dist: click
Requires-Dist: requests
Requires-Dist: beautifulsoup4
Requires-Dist: openai
Requires-Dist: python-dotenv
Requires-Dist: loguru
